tempfolder/__init__.py
tempfolder/core.py
tempfolder-0.4.1.dist-info/LICENSE
tempfolder-0.4.1.dist-info/WHEEL
tempfolder-0.4.1.dist-info/METADATA
tempfolder-0.4.1.dist-info/RECORD
