Metadata-Version: 2.1
Name: tempfolder
Version: 0.4.1
Summary: 🗂 Easily create temporary folders, add files into them and don't worry about deleting them, tempfolder will take care
Home-page: https://github.com/jalvaradosegura/tempfolder
License: MIT
Author: Jorge Alvarado
Author-email: alvaradosegurajorge@gmail.com
Requires-Python: >=3.8,<4.0
Classifier: License :: OSI Approved :: MIT License
Classifier: Programming Language :: Python :: 3
Classifier: Programming Language :: Python :: 3.8
Classifier: Programming Language :: Python :: 3.9
Project-URL: Repository, https://github.com/jalvaradosegura/tempfolder
